cats/CI_api_interface.py
cats/CI_api_query.py
cats/__init__.py
cats/__main__.py
cats/carbonFootprint.py
cats/config.yml
cats/configure.py
cats/constants.py
cats/forecast.py
cats/plotting.py
climate_aware_task_scheduler-1.1.0.dist-info/licenses/LICENSE
climate_aware_task_scheduler-1.1.0.dist-info/METADATA
climate_aware_task_scheduler-1.1.0.dist-info/WHEEL
climate_aware_task_scheduler-1.1.0.dist-info/entry_points.txt
climate_aware_task_scheduler-1.1.0.dist-info/top_level.txt
climate_aware_task_scheduler-1.1.0.dist-info/RECORD
