Metadata-Version: 2.4
Name: climate-aware-task-scheduler
Version: 1.1.0
Summary: Climate aware task scheduler
Author: Colin Sauze, Andrew Walker, Loïc Lannelongue, Thibault Lestang, Tony Greenberg, Lincoln Colling, Adam Ward, Abhishek Dasgupta, Carlos Martinez, Sadie Bartholomew
License: MIT License
Project-URL: Home, https://github.com/GreenScheduler/cats
Classifier: License :: OSI Approved :: MIT License
Classifier: Programming Language :: Python :: 3
Classifier: Development Status :: 5 - Production/Stable
Classifier: Environment :: Console
Classifier: Intended Audience :: Science/Research
Classifier: Intended Audience :: System Administrators
Requires-Python: >=3.9
License-File: LICENSE
Requires-Dist: requests-cache>=1.0
Requires-Dist: PyYAML>=6.0
Provides-Extra: test
Requires-Dist: pytest; extra == "test"
Requires-Dist: numpy>=1.5.0; extra == "test"
Requires-Dist: pytest-subprocess==1.5.0; extra == "test"
Requires-Dist: pytest-cov; extra == "test"
Requires-Dist: matplotlib>=3.0; extra == "test"
Provides-Extra: types
Requires-Dist: mypy; extra == "types"
Requires-Dist: types-PyYAML; extra == "types"
Requires-Dist: types-redis; extra == "types"
Requires-Dist: types-requests; extra == "types"
Requires-Dist: types-ujson; extra == "types"
Provides-Extra: docs
Requires-Dist: sphinx==6.*; extra == "docs"
Requires-Dist: sphinx-argparse; extra == "docs"
Requires-Dist: ghp-import; extra == "docs"
Requires-Dist: renku-sphinx-theme; extra == "docs"
Requires-Dist: sphinx_copybutton; extra == "docs"
Provides-Extra: plots
Requires-Dist: matplotlib>=3.0; extra == "plots"
Dynamic: license-file
